timetree_sdk/__init__.py
timetree_sdk/api.py
timetree_sdk/models/__init__.py
timetree_sdk/models/base.py
timetree_sdk/models/events.py
timetree_sdk/models/responses.py
timetree_sdk-0.1.3.dist-info/METADATA
timetree_sdk-0.1.3.dist-info/WHEEL
timetree_sdk-0.1.3.dist-info/top_level.txt
timetree_sdk-0.1.3.dist-info/RECORD
