Metadata-Version: 2.1
Name: timetree-sdk
Version: 0.1.3
Summary: TimeTree API SDK for Python
Home-page: https://github.com/morugu/timetree-sdk-python
Author: Shoya Shiraki
Author-email: shoya.shiraki@gmail.com
License: MIT
Keywords: TimeTree timetree time-tree api sdk
Platform: UNKNOWN
Classifier: Development Status :: 4 - Beta
Classifier: License :: OSI Approved :: MIT License
Classifier: Programming Language :: Python :: 3.8
